clearskies_twilio/__init__.py
clearskies_twilio/actions/__init__.py
clearskies_twilio/actions/sms.py
clearskies_twilio/actions/sms_test.py
clearskies_twilio/di/__init__.py
clearskies_twilio/di/twilio.py
clearskies_twilio/mocks/__init__.py
clearskies_twilio/mocks/actions/__init__.py
clearskies_twilio/mocks/actions/sms.py
clear_skies_twilio-0.9.4.dist-info/LICENSE
clear_skies_twilio-0.9.4.dist-info/METADATA
clear_skies_twilio-0.9.4.dist-info/WHEEL
clear_skies_twilio-0.9.4.dist-info/RECORD
