Metadata-Version: 2.1
Name: clear-skies-twilio
Version: 0.9.4
Summary: clearskies bindings for working with Twilio
Home-page: https://github.com/cmancone/clearskies-twilio
License: MIT
Author: Conor Mancone
Author-email: cmancone@gmail.com
Requires-Python: >=3.10,<4.0
Classifier: License :: OSI Approved :: MIT License
Classifier: Programming Language :: Python :: 3
Classifier: Programming Language :: Python :: 3.10
Classifier: Programming Language :: Python :: 3.11
Requires-Dist: clear-skies (>=1.19.24,<2.0.0)
Requires-Dist: twilio (>=9.0.5,<10.0.0)
Project-URL: Repository, https://github.com/cmancone/clearskies-twilio
